net_command/__init__.py
net_command/cli.py
net_command/inventory.py
net_command/output_handler.py
net_command/parallel_executor.py
net_command/playbook.py
net_command-0.1.0.dist-info/METADATA
net_command-0.1.0.dist-info/WHEEL
net_command-0.1.0.dist-info/entry_points.txt
net_command-0.1.0.dist-info/RECORD
