Metadata-Version: 2.1
Name: net-command
Version: 0.1.0
Summary: 
Author: Elinpf
Author-email: 365433079@qq.com
Requires-Python: >=3.8,<4.0
Classifier: Programming Language :: Python :: 3
Classifier: Programming Language :: Python :: 3.8
Classifier: Programming Language :: Python :: 3.9
Classifier: Programming Language :: Python :: 3.10
Classifier: Programming Language :: Python :: 3.11
Classifier: Programming Language :: Python :: 3.12
Classifier: Programming Language :: Python :: 3.13
Requires-Dist: netmiko (>=4.4.0,<5.0.0)
